ai_creator/__init__.py
ai_creator/main.py
ai_creator-0.0.1.dist-info/entry_points.txt
ai_creator-0.0.1.dist-info/METADATA
ai_creator-0.0.1.dist-info/WHEEL
ai_creator-0.0.1.dist-info/RECORD
