Metadata-Version: 2.1
Name: ai-creator
Version: 0.0.1
Summary: 
Author: Kevin Pflaumer
Author-email: kevin@pflaumer.at
Requires-Python: >=3.9,<4.0
Classifier: Programming Language :: Python :: 3
Classifier: Programming Language :: Python :: 3.9
Classifier: Programming Language :: Python :: 3.10
Classifier: Programming Language :: Python :: 3.11
Requires-Dist: typer[all] (>=0.9.0,<0.10.0)
